hanjaq/__init__.py
hanjaq/dictionary.py
hanjaq/exception.py
hanjaq/hanja.py
hanjaq/hanja.txt
tests/functional/__init__.py
tests/functional/test_get_hanja_information.py
tests/functional/test_is_hanja.py
tests/unit/__init__.py
tests/unit/test_dictionary.py
tests/unit/test_hanja.py
hanjaq-0.0.3.dist-info/LICENSE
hanjaq-0.0.3.dist-info/METADATA
hanjaq-0.0.3.dist-info/WHEEL
hanjaq-0.0.3.dist-info/top_level.txt
hanjaq-0.0.3.dist-info/RECORD
