Metadata-Version: 2.1
Name: hanjaq
Version: 0.0.3
Summary: Used to get meanings and hangul representations of Hanja.
Home-page: https://github.com/alanverresen/hanjaq
Author: Alan Verresen
Author-email: hanjaq@alanverresen.com
License: MIT
Keywords: Korean,Hanja,Hangul,vocabulary,words,word origins,etymology,한국어,한자,한글,어휘,단어,어원
Platform: UNKNOWN
Classifier: Development Status :: 3 - Alpha
Classifier: License :: OSI Approved :: MIT License
Classifier: Programming Language :: Python :: 3
Classifier: Programming Language :: Python :: 3.7
Classifier: Programming Language :: Python :: 3.8
Requires-Python: >=3.7
